zemfrog_test/__init__.py
zemfrog_test/command.py
zemfrog_test/fixtures.py
zemfrog_test/generator.py
zemfrog_test/helper.py
zemfrog_test/templates/tests/apis/.gitkeep
zemfrog_test/templates/tests/blueprints/.gitkeep
zemfrog_test/templates/tests/conftest.py
zemfrog_test/templates/unittest.py
zemfrog_test-1.0.3.dist-info/entry_points.txt
zemfrog_test-1.0.3.dist-info/LICENSE
zemfrog_test-1.0.3.dist-info/WHEEL
zemfrog_test-1.0.3.dist-info/METADATA
zemfrog_test-1.0.3.dist-info/RECORD
