Metadata-Version: 2.1
Name: zemfrog-test
Version: 1.0.3
Summary: Zemfrog unit testing tools
License: MIT
Keywords: zemfrog
Author: aprilahijriyan
Author-email: hijriyan23@gmail.com
Requires-Python: >=3.7,<4.0
Classifier: Development Status :: 4 - Beta
Classifier: Framework :: Flask
Classifier: Intended Audience :: Developers
Classifier: License :: OSI Approved :: MIT License
Classifier: Natural Language :: English
Classifier: Programming Language :: Python :: 3
Classifier: Programming Language :: Python :: 3.7
Classifier: Programming Language :: Python :: 3.8
Classifier: Programming Language :: Python :: 3.9
Requires-Dist: pytest (>=6.2.2,<7.0.0)
Requires-Dist: zemfrog (>=5.0.1,<6.0.0)
Project-URL: Donation, https://www.patreon.com/aprilahijriyan
Project-URL: Github, https://github.com/zemfrog/zemfrog-test
Project-URL: Issue Tracker, https://github.com/zemfrog/zemfrog-test/issues
